xbom_lib/__init__.py
xbom_lib/blint.py
xbom_lib/cdxgen.py
ds_xbom_lib-6.0.0.dist-info/METADATA
ds_xbom_lib-6.0.0.dist-info/WHEEL
ds_xbom_lib-6.0.0.dist-info/top_level.txt
ds_xbom_lib-6.0.0.dist-info/RECORD
